README.md
setup.py
vdt/__init__.py
vdt.versionplugin.default.egg-info/PKG-INFO
vdt.versionplugin.default.egg-info/SOURCES.txt
vdt.versionplugin.default.egg-info/dependency_links.txt
vdt.versionplugin.default.egg-info/namespace_packages.txt
vdt.versionplugin.default.egg-info/requires.txt
vdt.versionplugin.default.egg-info/top_level.txt
vdt.versionplugin.default.egg-info/zip-safe
vdt/versionplugin/__init__.py
vdt/versionplugin/default/__init__.py
vdt/versionplugin/default/package.py
vdt/versionplugin/default/version.py