Metadata-Version: 1.2
Name: vdt.versionplugin.default
Version: 0.0.3
Summary: Default Version Increment Plugin for GIT
Home-page: UNKNOWN
Author: Lars van de Kerkhof
Author-email: lars@devopsconsulting.nl
Maintainer: Lars van de Kerkhof
Maintainer-email: lars@devopsconsulting.nl
License: UNKNOWN
Platform: UNKNOWN
